candig_server-1.4.0-py3.6-nspkg.pth
candig/server/DP.py
candig/server/NCIT.py
candig/server/__init__.py
candig/server/_version.py
candig/server/backend.py
candig/server/configtest.py
candig/server/datarepo.py
candig/server/exceptions.py
candig/server/frontend.py
candig/server/gff3.py
candig/server/ontology.py
candig/server/paging.py
candig/server/response_builder.py
candig/server/serverconfig.py
candig/server/sqlite_backend.py
candig/server/stuff.cfg
candig/server/auth/__init__.py
candig/server/cli/__init__.py
candig/server/cli/configtest.py
candig/server/cli/repomanager.py
candig/server/cli/server.py
candig/server/config/client_secrets.json
candig/server/datamodel/__init__.py
candig/server/datamodel/bio_metadata.py
candig/server/datamodel/clinical_metadata.py
candig/server/datamodel/continuous.py
candig/server/datamodel/datasets.py
candig/server/datamodel/genotype_phenotype.py
candig/server/datamodel/genotype_phenotype_featureset.py
candig/server/datamodel/obo_parser.py
candig/server/datamodel/ontologies.py
candig/server/datamodel/peers.py
candig/server/datamodel/pipeline_metadata.py
candig/server/datamodel/reads.py
candig/server/datamodel/references.py
candig/server/datamodel/rna_quantification.py
candig/server/datamodel/sequence_annotations.py
candig/server/datamodel/variants.py
candig/server/network/__init__.py
candig/server/repo/__init__.py
candig/server/repo/models.py
candig/server/repo/rnaseq2ga.py
candig/server/static/favicon.ico
candig/server/static/readme.md
candig/server/static/robots.txt
candig/server/static/assets/css/paper-dashboard.css
candig/server/static/assets/css/paper-dashboard.css.map
candig/server/static/assets/css/paper-dashboard.min.css
candig/server/static/assets/img/favicon.ico
candig/server/static/assets/img/logo.png
candig/server/static/assets/img/logo_pic.png
candig/server/static/assets/js/paper-dashboard.js
candig/server/static/assets/js/paper-dashboard.min.js
candig/server/static/assets/scss/paper-dashboard.scss
candig_server-1.4.0.dist-info/LICENSE
candig_server-1.4.0.dist-info/METADATA
candig_server-1.4.0.dist-info/WHEEL
candig_server-1.4.0.dist-info/entry_points.txt
candig_server-1.4.0.dist-info/namespace_packages.txt
candig_server-1.4.0.dist-info/top_level.txt
candig_server-1.4.0.dist-info/RECORD
